{"name":"se llena formulario para contactar","id":"aventaja;se-llena-formulario-para-contactar","testSteps":[{"number":1,"description":"When Se retorna a la pagina de inicio","duration":6411,"startTime":"2023-10-18T00:14:42.525-06:00[America/Regina]","result":"SUCCESS","precondition":false,"level":0},{"number":2,"description":"And Se llena formulario Contacto","duration":150296,"startTime":"2023-10-18T00:14:48.944-06:00[America/Regina]","result":"SUCCESS","precondition":false,"level":0},{"number":3,"description":"And Se selecciona boton enviar","duration":10185,"startTime":"2023-10-18T00:17:19.242-06:00[America/Regina]","result":"SUCCESS","precondition":false,"level":0}],"userStory":{"id":"aventaja","storyName":"aventaja","path":"src/test/resources/features/aventaja.feature","type":"feature"},"featureTag":{"name":"Features/aventaja","type":"feature","displayName":"Features/aventaja"},"title":"se llena formulario para contactar","tags":[{"name":"contactar","type":"tag","displayName":"contactar"},{"name":"aventaja","type":"feature","displayName":"aventaja"}],"startTime":"2023-10-18T00:14:42.512-06:00[America/Regina]","duration":166920,"projectKey":"","isManualTestingUpToDate":false,"manual":false,"testSource":"Cucumber","result":"SUCCESS"}